py_disinfection/__init__.py
py_disinfection/cli.py
py_disinfection/core.py
py_disinfection/estimation.py
py_disinfection/tables.py
py_disinfection-0.1.11.dist-info/AUTHORS.rst
py_disinfection-0.1.11.dist-info/LICENSE
py_disinfection-0.1.11.dist-info/METADATA
py_disinfection-0.1.11.dist-info/WHEEL
py_disinfection-0.1.11.dist-info/entry_points.txt
py_disinfection-0.1.11.dist-info/top_level.txt
py_disinfection-0.1.11.dist-info/RECORD
