Metadata-Version: 2.2
Name: py_disinfection
Version: 0.1.11
Summary: Library and command to calculate detention times, disinfectant residuals, and CT ratios for drinking water systems
Author-email: Sylvie Water Systems <hello@sylviewater.com>
Maintainer-email: Sylvie Water Systems <hello@sylviewater.com>
License: BSD license
Project-URL: bugs, https://github.com/toddrbryan/py_disinfection/issues
Project-URL: changelog, https://github.com/toddrbryan/py_disinfection/blob/master/changelog.md
Project-URL: homepage, https://github.com/toddrbryan/py_disinfection
Classifier: Development Status :: 4 - Beta
Classifier: Intended Audience :: Developers
Classifier: License :: OSI Approved :: BSD License
Classifier: Programming Language :: Python :: 3
Classifier: Programming Language :: Python :: 3.8
Classifier: Programming Language :: Python :: 3.9
Classifier: Programming Language :: Python :: 3.10
Classifier: Programming Language :: Python :: 3.11
Classifier: Programming Language :: Python :: 3.12
Classifier: Topic :: Scientific/Engineering
Classifier: Topic :: Utilities
Requires-Python: >=3.6
License-File: LICENSE
License-File: AUTHORS.rst
Requires-Dist: typer
Requires-Dist: rich
Requires-Dist: pydantic>=2.0
Provides-Extra: dev
Requires-Dist: coverage; extra == "dev"
Requires-Dist: mypy; extra == "dev"
Requires-Dist: pytest; extra == "dev"
Requires-Dist: pytest-cov; extra == "dev"
Requires-Dist: ruff; extra == "dev"
Requires-Dist: twine; extra == "dev"
Requires-Dist: types-pydantic; extra == "dev"
